epyscan/__init__.py
epyscan/_version.py
epyscan-0.2.0.dist-info/licenses/LICENCE.md
epyscan-0.2.0.dist-info/METADATA
epyscan-0.2.0.dist-info/WHEEL
epyscan-0.2.0.dist-info/top_level.txt
epyscan-0.2.0.dist-info/RECORD
