Metadata-Version: 2.4
Name: epyscan
Version: 0.2.0
Summary: Create campaigns of EPOCH plasma PIC code runs over a given parameter space using various sampling methods.
Author-email: Peter Hill <peter.hill@york.ac.uk>, Joel Adams <joel.adams@york.ac.uk>, Lawrence Dior <lfnd500@york.ac.uk>
License:                     GNU GENERAL PUBLIC LICENSE
Requires-Python: >=3.9
License-File: LICENCE.md
Requires-Dist: epydeck>=1.0.0
Requires-Dist: numpy>=1.24
Requires-Dist: scipy>=1.10
Provides-Extra: docs
Requires-Dist: sphinx>=5.3; extra == "docs"
Requires-Dist: sphinx_autodoc_typehints>=1.19; extra == "docs"
Requires-Dist: sphinx-book-theme>=0.4.0rc1; extra == "docs"
Requires-Dist: sphinx-argparse-cli>=1.10.0; extra == "docs"
Requires-Dist: sphinx-inline-tabs; extra == "docs"
Provides-Extra: tests
Requires-Dist: pytest>=3.3.0; extra == "tests"
Provides-Extra: lint
Requires-Dist: ruff; extra == "lint"
Dynamic: license-file
